astroviper-0.0.30.dist-info/WHEEL
astroviper-0.0.30.dist-info/METADATA
astroviper-0.0.30.dist-info/RECORD
astroviper-0.0.30.dist-info/licenses/LICENSE.txt
astroviper/__init__.py
astroviper/utils/plotting.py
astroviper/utils/data_partitioning.py
astroviper/utils/check_logger_params.py
astroviper/utils/check_params.py
astroviper/utils/__init__.py
astroviper/core/__init__.py
astroviper/core/calibration/__init.py__
astroviper/core/image_analysis/__init.py__
astroviper/core/image_analysis/moment_max.py
astroviper/core/image_analysis/psf_gaussian_fit.py
astroviper/core/imaging/fft.py
astroviper/core/imaging/make_gridding_convolution_function.py
astroviper/core/imaging/fft_norm_img_xds.py
astroviper/core/imaging/feather.py
astroviper/core/imaging/check_imaging_parameters.py
astroviper/core/imaging/deconvolution.py
astroviper/core/imaging/calculate_imaging_weights.py
astroviper/core/imaging/make_visibility_grid.py
astroviper/core/imaging/make_aperture_grid.py
astroviper/core/imaging/make_uv_sampling_grid.py
astroviper/core/imaging/__init__.py
astroviper/core/imaging/ifft.py
astroviper/core/imaging/imaging_weighting/briggs_weighting.py
astroviper/core/imaging/imaging_weighting/grid_imaging_weights.py
astroviper/core/imaging/imaging_weighting/__init__.py
astroviper/core/imaging/imaging_utils/make_pb_symmetric.py
astroviper/core/imaging/imaging_utils/mosaic_grid.py
astroviper/core/imaging/imaging_utils/gcf_prolate_spheroidal.py
astroviper/core/imaging/imaging_utils/__init__.py
astroviper/core/imaging/imaging_utils/standard_grid.py
astroviper/core/imaging/imaging_utils/standard_gridding_example.py
astroviper/core/imaging/imaging_utils/bu/single_cf_gridder.cpp
astroviper/core/imaging/imaging_utils/bu/single_cf_gridder_numba.py
astroviper/core/imaging/imaging_utils/bu/pybind11_wrapper.cpp
astroviper/core/imaging/imaging_utils/bu/single_cf_gridder.h
astroviper/core/imaging/deconvolvers/__init__.py
astroviper/core/imaging/deconvolvers/hogbom/_hogbom_ext.cpython-311-x86_64-linux-gnu.so
astroviper/core/imaging/deconvolvers/hogbom/CMakeLists.txt
